seo/__init__.py
seo/generators.py
seo/utils.py
seo/templates/debutant/app.py
seo/templates/debutant/index.html
seo/templates/debutant/style.css
seo/templates/intermediaire/config.py
seo/templates/intermediaire/run.py
seo/templates/intermediaire/app/__init__.py
seo/templates/intermediaire/app/models.py
seo/templates/intermediaire/app/routes.py
seo/templates/pro/docker-compose.yml
seo/templates/pro/app/__init__.py
seo/templates/pro/app/api/__init__.py
seo/templates/pro/app/api/v1/__init__.py
seo/templates/pro/app/api/v1/endpoints.py
seo/templates/pro/app/core/config.py
seo/templates/pro/app/core/security.py
seo/templates/pro/app/db/base.py
seo/templates/pro/app/db/models.py
seo_dev_env-0.1.0.dist-info/licenses/LICENSE.ls
seo_dev_env-0.1.0.dist-info/METADATA
seo_dev_env-0.1.0.dist-info/WHEEL
seo_dev_env-0.1.0.dist-info/entry_points.txt
seo_dev_env-0.1.0.dist-info/top_level.txt
seo_dev_env-0.1.0.dist-info/RECORD
