Metadata-Version: 2.4
Name: seo-dev-env
Version: 0.1.0
Summary: Générateur d'environnements de développement pour tous niveaux
Home-page: https://github.com/https://github.com/elkast/seo-dev-env
Author: Votre Nom
Author-email: orsinimelchisedek@gmail.com
Classifier: Programming Language :: Python :: 3
Classifier: License :: OSI Approved :: MIT License
Classifier: Operating System :: OS Independent
Requires-Python: >=3.6
License-File: LICENSE.ls
Requires-Dist: flask>=2.0.0
Requires-Dist: python-dotenv>=0.19.0
Dynamic: author
Dynamic: author-email
Dynamic: classifier
Dynamic: description
Dynamic: description-content-type
Dynamic: home-page
Dynamic: license-file
Dynamic: requires-dist
Dynamic: requires-python
Dynamic: summary
